clauth/__init__.py
clauth/aws_utils.py
clauth/cli.py
clauth/config.py
clauth/helpers.py
clauth/launcher.py
clauth/commands/__init__.py
clauth/commands/config.py
clauth/commands/delete.py
clauth/commands/init.py
clauth/commands/models.py
clauth/ui/__init__.py
clauth/ui/components.py
clauth/ui/theme.py
clauth-0.1.6.dist-info/METADATA
clauth-0.1.6.dist-info/WHEEL
clauth-0.1.6.dist-info/entry_points.txt
clauth-0.1.6.dist-info/licenses/LICENSE
clauth-0.1.6.dist-info/RECORD
