Metadata-Version: 2.4
Name: clauth
Version: 0.1.6
Summary: Streamlined AWS Bedrock setup for Claude Code - automated SSO, model discovery, and environment configuration
Project-URL: Homepage, https://github.com/khordoo/clauth
Project-URL: Repository, https://github.com/khordoo/clauth
Project-URL: Documentation, https://github.com/khordoo/clauth#readme
Project-URL: Bug Tracker, https://github.com/khordoo/clauth/issues
Author: Mahmood Khordoo
License: MIT
License-File: LICENSE
Keywords: ai,anthropic,authentication,aws,bedrock,claude,cli,llm,sso
Classifier: Development Status :: 4 - Beta
Classifier: Environment :: Console
Classifier: Intended Audience :: Developers
Classifier: Intended Audience :: System Administrators
Classifier: Operating System :: OS Independent
Classifier: Programming Language :: Python :: 3
Classifier: Programming Language :: Python :: 3.10
Classifier: Programming Language :: Python :: 3.11
Classifier: Programming Language :: Python :: 3.12
Classifier: Topic :: Internet :: WWW/HTTP :: Session
Classifier: Topic :: Software Development :: Libraries :: Python Modules
Classifier: Topic :: System :: Systems Administration
Requires-Python: >=3.10
Requires-Dist: boto3>=1.40.31
Requires-Dist: inquirerpy>=0.3.4
Requires-Dist: pydantic>=2.0.0
Requires-Dist: pyfiglet>=1.0.4
Requires-Dist: rich>=13.7.1
Requires-Dist: toml>=0.10.2
Requires-Dist: typer>=0.17.4
Provides-Extra: dev
Requires-Dist: moto>=5.1.12; extra == 'dev'
Requires-Dist: pytest-cov>=7.0.0; extra == 'dev'
Requires-Dist: pytest-mock>=3.15.1; extra == 'dev'
Requires-Dist: pytest>=8.4.2; extra == 'dev'
Provides-Extra: test
Requires-Dist: moto>=4.0.0; extra == 'test'
Requires-Dist: pytest-cov>=4.0.0; extra == 'test'
Requires-Dist: pytest-mock>=3.10.0; extra == 'test'
Requires-Dist: pytest>=7.0.0; extra == 'test'
